README.md
setup.py
gpxMap/__init__.py
gpxMap.egg-info/PKG-INFO
gpxMap.egg-info/SOURCES.txt
gpxMap.egg-info/dependency_links.txt
gpxMap.egg-info/requires.txt
gpxMap.egg-info/top_level.txt